gprofiler_custom_gmt/__init__.py
gprofiler_custom_gmt/main.py
gprofiler_custom_gmt/test.gmt
gprofiler_custom_gmt-0.1.1.dist-info/entry_points.txt
gprofiler_custom_gmt-0.1.1.dist-info/WHEEL
gprofiler_custom_gmt-0.1.1.dist-info/METADATA
gprofiler_custom_gmt-0.1.1.dist-info/RECORD
