Metadata-Version: 2.1
Name: gprofiler-custom-gmt
Version: 0.1.1
Summary: 
Author: Hugo Martiniano
Author-email: hugomartiniano@gmail.com
Requires-Python: >=3.7.1,<4.0.0
Classifier: Programming Language :: Python :: 3
Classifier: Programming Language :: Python :: 3.8
Classifier: Programming Language :: Python :: 3.9
Requires-Dist: gprofiler-official (>=1.0.0,<2.0.0)
Requires-Dist: pandas (>=1.2.3,<2.0.0)
Requires-Dist: requests (>=2.25.1,<3.0.0)
